efris/__init__.py
efris/invoicing.py
efris/output_cleaner.py
efris/payload.py
efris/services.py
efris/test_invoicing.py
efris/utils.py
efriser/__init__.py
efriser/invoicing.py
efriser/output_cleaner.py
efriser/payload.py
efriser/services.py
efriser/utils.py
efriser-0.1.10.dist-info/METADATA
efriser-0.1.10.dist-info/WHEEL
efriser-0.1.10.dist-info/top_level.txt
efriser-0.1.10.dist-info/RECORD
